bless/__init__.py
bless/exceptions.py
bless/py.typed
bless/backends/__init__.py
bless/backends/characteristic.py
bless/backends/server.py
bless/backends/service.py
bless/backends/bluezdbus/__init__.py
bless/backends/bluezdbus/characteristic.py
bless/backends/bluezdbus/server.py
bless/backends/bluezdbus/service.py
bless/backends/bluezdbus/dbus/__init__.py
bless/backends/bluezdbus/dbus/advertisement.py
bless/backends/bluezdbus/dbus/application.py
bless/backends/bluezdbus/dbus/characteristic.py
bless/backends/bluezdbus/dbus/service.py
bless/backends/bluezdbus/dbus/utils.py
bless/backends/corebluetooth/__init__.py
bless/backends/corebluetooth/characteristic.py
bless/backends/corebluetooth/error.py
bless/backends/corebluetooth/peripheral_manager_delegate.py
bless/backends/corebluetooth/server.py
bless/backends/corebluetooth/service.py
bless/backends/winrt/__init__.py
bless/backends/winrt/characteristic.py
bless/backends/winrt/server.py
bless/backends/winrt/service.py
bless/backends/winrt/ble/__init__.py
bless/backends/winrt/ble/adapter.py
bless-0.2.6.dist-info/LICENSE
bless-0.2.6.dist-info/METADATA
bless-0.2.6.dist-info/WHEEL
bless-0.2.6.dist-info/top_level.txt
bless-0.2.6.dist-info/RECORD
