Metadata-Version: 2.1
Name: bless
Version: 0.2.6
Summary: A Bluetooth Low Energy Server supplement to Bleak
Home-page: https://github.com/kevincar/bless
Author: Kevin Davis
Author-email: kevincarrolldavis@gmail.com
Classifier: Programming Language :: Python :: 3
Classifier: License :: OSI Approved :: MIT License
Classifier: Operating System :: OS Independent
Requires-Python: >=3.7
License-File: LICENSE
